notifier/__init__.py
notifier/controller.py
providers/__init__.py
providers/email.py
providers/slack.py
utils/__init__.py
utils/exceptions.py
utils/helpers.py
notification_services-0.2.dist-info/METADATA
notification_services-0.2.dist-info/WHEEL
notification_services-0.2.dist-info/top_level.txt
notification_services-0.2.dist-info/RECORD
